jl95/pytools/ppcmd.py
jl95/pytools/pphtml.py
jl95/pytools/pptoml.py
jl95/pytools/ppyaml.py
jl95/pytools/pp/__init__.py
jl95terceira/pytools/ppcmd.py
jl95terceira/pytools/pphtml.py
jl95terceira/pytools/pptoml.py
jl95terceira/pytools/ppyaml.py
jl95terceira/pytools/pp/__init__.py
jl95terceira_pytools_pp-0.3.1.dist-info/METADATA
jl95terceira_pytools_pp-0.3.1.dist-info/WHEEL
jl95terceira_pytools_pp-0.3.1.dist-info/entry_points.txt
jl95terceira_pytools_pp-0.3.1.dist-info/RECORD
