Metadata-Version: 2.4
Name: jl95terceira_pytools_pp
Version: 0.3.1
Summary: A module to develop text file pre-processors for programming / markdown / etc languages
Project-URL: Homepage, https://github.com/jl95terceira/project-pp
Project-URL: Issues, https://github.com/jl95terceira/project-pp/issues
Author-email: Joao Luis Ornelas da Silva <jl95terceira@gmail.com>
Classifier: License :: OSI Approved :: MIT License
Classifier: Operating System :: OS Independent
Classifier: Programming Language :: Python :: 3
Requires-Python: >=3.12
